MANIFEST.in
README.rst
requirements.txt
requirements_dev.txt
setup.cfg
setup.py
biloba/__init__.py
biloba/_pkg_meta.py
biloba/config.py
biloba/events.py
biloba/service.py
biloba/util.py
biloba.egg-info/PKG-INFO
biloba.egg-info/SOURCES.txt
biloba.egg-info/dependency_links.txt
biloba.egg-info/requires.txt
biloba.egg-info/top_level.txt
biloba/ext/__init__.py
biloba/test/__init__.py
biloba/test/test_config.py
biloba/test/test_events.py
biloba/test/test_service.py
biloba/test/test_util.py