Metadata-Version: 1.0
Name: biloba
Version: 3.0.0
Summary: Provides gevent primitives to orchestrate different orthogonal servers and services together.
Home-page: https://github.com/njoyce/biloba
Author: Nick Joyce
Author-email: nick@boxdesign.co.uk
License: UNKNOWN
Platform: UNKNOWN
